facer/__init__.py
facer/facer.py
facer/typing.py
facer/utils.py
average_facer-0.7.6.dist-info/LICENSE
average_facer-0.7.6.dist-info/METADATA
average_facer-0.7.6.dist-info/WHEEL
average_facer-0.7.6.dist-info/RECORD
