Metadata-Version: 2.1
Name: average-facer
Version: 0.7.6
Summary: Face averaging in Python made simple.
Home-page: https://github.com/johnwmillr/Facer
License: MIT
Keywords: opencv,image-processing,face-detection,dlib,face-average,facer,face-averaging,average-facer
Author: John William Ruth Miller
Author-email: john.w.millr@gmail.com
Requires-Python: >=3.10,<4.0
Classifier: License :: OSI Approved :: MIT License
Classifier: Programming Language :: Python :: 3
Classifier: Programming Language :: Python :: 3.10
Classifier: Programming Language :: Python :: 3.11
Classifier: Programming Language :: Python :: 3.12
Classifier: Programming Language :: Python :: 3.13
Requires-Dist: dlib (>=19,<20)
Requires-Dist: ffmpeg-python (>=0.2,<0.3)
Requires-Dist: matplotlib (>=3,<4)
Requires-Dist: opencv-python (>=4,<5)
Requires-Dist: tqdm (>=4,<5)
Project-URL: Blog Post, https://www.johnwmillr.com/average-faces-in-python/
Project-URL: Faces of Fortune, https://www.johnwmillr.com/faces-of-fortune/
Project-URL: PyPI, https://pypi.org/project/average-facer/
Project-URL: Repository, https://github.com/johnwmillr/Facer
